suggestify/__init__.py
suggestify/logo.txt
suggestify/utils.py
suggestify/api/django_adapter.py
suggestify/api/fastapi_adapter.py
suggestify/api/flask_adapter.py
suggestify/core/__init__.py
suggestify/core/database.py
suggestify/core/fuzzy.py
suggestify/core/suggester.py
suggestify-0.1.2.dist-info/METADATA
suggestify-0.1.2.dist-info/WHEEL
suggestify-0.1.2.dist-info/top_level.txt
suggestify-0.1.2.dist-info/RECORD
