Metadata-Version: 2.4
Name: suggestify
Version: 0.1.2
Summary: Domain-agnostic semantic query suggestion engine
Home-page: https://github.com/MD-Jubayer-Khan/suggestify
Author: MD Jubayer Khan
Project-URL: Documentation, https://github.com/MD-Jubayer-Khan/suggestify#readme
Project-URL: Source, https://github.com/MD-Jubayer-Khan/suggestify
Project-URL: Bug Tracker, https://github.com/MD-Jubayer-Khan/suggestify/issues
Keywords: query suggestion NLP semantic search fuzzy search AI
Classifier: Programming Language :: Python :: 3
Classifier: License :: OSI Approved :: MIT License
Classifier: Operating System :: OS Independent
Requires-Python: >=3.10
Requires-Dist: sentence-transformers>=2.2.2
Requires-Dist: torch>=2.0.0
Requires-Dist: pandas>=2.0.0
Requires-Dist: rapidfuzz>=3.14.3
Requires-Dist: SQLAlchemy>=2.0.0
Requires-Dist: wikipedia-api>=0.5.8
Requires-Dist: spacy>=3.6.0
Dynamic: author
Dynamic: classifier
Dynamic: description
Dynamic: description-content-type
Dynamic: home-page
Dynamic: keywords
Dynamic: project-url
Dynamic: requires-dist
Dynamic: requires-python
Dynamic: summary
